Workbook

Sheet Продавцы
A1: № | B1: Продавец / торговая сеть | C1: Домен | D1: Код направления | E1: Направление деятельности | F1: Тип игрока | G1: Бренды элементов питания в ассортименте | H1: СТМ / собственная марка | I1: Выбор региона | J1: Как устроена региональность | K1: Пример региональных URL | L1: Ссылка на страницу «Батарейки» | M1: Статус проверки
A2: 1 | B2: Ozon | C2: ozon.ru | D2: MP | E2: Маркетплейс | F2: Маркетплейс 1P+3P | G2: Весь спектр: GP, Duracell, Energizer, Varta, Panasonic, Camelion, Kodak, Robiton, SmartBuy, ЭРА | H2: Нет (есть Ozon Basic у части селлеров) | I2: Единая карточка | J2: Один URL карточки на всю РФ. Регион меняет цену, срок и наличие, но не адрес страницы | K2: — | L2: https://www.ozon.ru/category/batareyki-15882/ | M2: Проверено
A3: 2 | B3: Wildberries | C3: wildberries.ru | D3: MP | E3: Маркетплейс | F3: Маркетплейс 3P | G3: Весь спектр: Duracell, Energizer, GP, Varta, Camelion, SmartBuy, Perfeo, ЭРА | H3: Нет | I3: Единая карточка | J3: Единый артикул на РФ; регион влияет на срок доставки до ПВЗ, URL неизменен | K3: — | L3: https://www.wildberries.ru/catalog/elektronika/tags/elementy-pitanija | M3: Проверено
A4: 3 | B4: Яндекс Маркет | C4: market.yandex.ru | D4: MP | E4: Маркетплейс | F4: Маркетплейс 3P + витрина сравнения | G4: Duracell, Energizer, GP, Kodak, Commo, Sonnen, Perfeo и др. | H4: Commo (СТМ Яндекса) | I4: Единая карточка | J4: Карточка модели общая на РФ, региональность — в блоке офферов и сроках доставки | K4: — | L4: https://market.yandex.ru/catalog--batareiki-i-akkumuliatory-dlia-audio-i-videotekhniki/26914470/list | M4: Проверено
A5: 4 | B5: Мегамаркет | C5: megamarket.ru | D5: MP | E5: Маркетплейс | F5: Маркетплейс 3P (экосистема Сбер) | G5: GP, Duracell, Energizer, Varta, АШАН Красная птица, Magnit и др. | H5: Нет | I5: Единая карточка | J5: Единый URL категории и карточки, регион переключается селектором | K5: — | L5: https://megamarket.ru/catalog/batarejki/ | M5: Проверено
A6: 5 | B6: AliExpress Россия | C6: aliexpress.ru | D6: MP | E6: Маркетплейс | F6: Маркетплейс 3P (локальные + трансграничные) | G6: Преимущественно азиатские марки + GP, Panasonic, SmartBuy | H6: Нет | I6: Единая карточка | J6: Единый URL товара, регион влияет на доступность локального склада | K6: — | L6: https://aliexpress.ru/ | M6: Требует уточнения (домен не открылся для проверки)
A7: 6 | B7: Авито | C7: avito.ru | D7: MP | E7: Маркетплейс | F7: Классифайд + маркетплейс товаров | G7: Разрозненный ассортимент от продавцов | H7: Нет | I7: Есть версии | J7: Объявление публикуется в конкретном городе; выдача и URL включают гео-сегмент | K7: avito.ru/moskva/... vs avito.ru/sankt-peterburg/... | L7: https://www.avito.ru/ | M7: Не проверено (сайт закрыт для краулера)
A8: 7 | B8: DNS | C8: dns-shop.ru | D8: EL | E8: Электроника и бытовая техника | F8: Федеральная сеть техники (омниканал) | G8: Duracell, GP, Energizer, Varta, Panasonic, Camelion, Robiton, SmartBuy, Kodak | H8: Есть (собственные марки DNS) | I8: Единая карточка | J8: Один URL на РФ, город выбирается селектором; цена и наличие отличаются по городам | K8: — | L8: https://www.dns-shop.ru/catalog/17a88ded16404e77/batarejki/ | M8: Проверено
A9: 8 | B9: Ситилинк | C9: citilink.ru | D9: EL | E9: Электроника и бытовая техника | F9: Федеральная сеть техники (онлайн + ПВЗ) | G9: Duracell, VARTA, GP, Energizer, Camelion, SmartBuy | H9: Есть | I9: Единая карточка | J9: Единый URL категории/бренда, город в заголовке страницы (напр. «— Москва») | K9: — | L9: https://www.citilink.ru/catalog/batareiki/ | M9: Проверено
A10: 9 | B10: М.Видео | C10: mvideo.ru | D10: EL | E10: Электроника и бытовая техника | F10: Федеральная сеть техники (омниканал) | G10: GP, Duracell, Energizer, Varta, Panasonic, Kodak, Carrera | H10: Carrera (СТМ группы М.Видео-Эльдорадо) | I10: Единая карточка | J10: Единый URL, фильтр по бренду в query; регион — селектором | K10: — | L10: https://www.mvideo.ru/aksessuary-dlya-doma-50/batareiki-i-akkumulyatory-296 | M10: Проверено
A11: 10 | B11: Эльдорадо | C11: eldorado.ru | D11: EL | E11: Электроника и бытовая техника | F11: Федеральная сеть техники (омниканал) | G11: GP Extra Alkaline, Kodak Xtralife, Energizer, Carrera, CROMEX | H11: Carrera (СТМ группы М.Видео-Эльдорадо) | I11: Единая карточка | J11: Единый URL категории, регион переключается селектором | K11: — | L11: https://www.eldorado.ru/c/batareyki/ | M11: Проверено
A12: 11 | B12: Технопарк | C12: technopark.ru | D12: EL | E12: Электроника и бытовая техника | F12: Сеть техники (Москва + онлайн по РФ) | G12: GP, Duracell, Energizer, Varta, Camelion | H12: Нет | I12: Единая карточка | J12: Единый URL раздела «Элементы питания» | K12: — | L12: https://www.technopark.ru/elementy-pitaniya/ | M12: Проверено
A13: 12 | B13: ОНЛАЙН ТРЕЙД.РУ | C13: onlinetrade.ru | D13: EL | E13: Электроника и бытовая техника | F13: Онлайн-ритейлер техники + ПВЗ | G13: VARTA, GP, Duracell, Panasonic, Energizer, Robiton | H13: Нет | I13: Единая карточка | J13: Единый URL карточки, регион — селектором города/ПВЗ | K13: — | L13: https://www.onlinetrade.ru/catalogue/batareyki-c59/ | M13: Проверено
... A53: 52 | B53: Детский мир | C53: detmir.ru | D53: FMCG | E53: Продукты и FMCG-ритейл | F53: Сеть детских товаров (батарейки к игрушкам) | G53: GP, Duracell, Energizer, Varta, Camelion | H53: Есть | I53: Единая карточка | J53: Единый URL категории, доставка по РФ (Москва, СПб, Н.Новгород, Челябинск, Новосибирск, Тюмень и др.) | K53: — | L53: https://www.detmir.ru/catalog/index/name/batteries1/ | M53: Проверено

Sheet Классификатор
A1: Код | B1: Направление деятельности | C1: Что относим | D1: Примеры
A2: MP | B2: Маркетплейс | C2: Универсальная площадка с внешними продавцами (3P), категория ведётся селлерами | D2: Ozon, Wildberries, Яндекс Маркет
A3: EL | B3: Электроника и бытовая техника | C3: Специализированный ритейл техники; батарейки — сопутствующая категория/аксессуар | D3: DNS, Ситилинк, М.Видео
A4: FMCG | B4: Продукты и FMCG-ритейл | C4: Продуктовые сети (гипер-/супермаркеты), батарейки в прикассовой и нон-фуд зоне | D4: Магнит, Лента, METRO
A5: DIY | B5: DIY, ремонт и товары для дома | C5: Стройматериалы, электрика, инструмент; батарейки в электротоварах | D5: Лемана ПРО, ВсеИнструменты, Петрович
A6: DROG | B6: Дрогери и фикс-прайс | C6: Нон-фуд FMCG с низким средним чеком, высокая доля СТМ | D6: Fix Price, Улыбка радуги, Галамарт
A7: B2B | B7: Офис, канцелярия и B2B-опт | C7: Снабжение юрлиц, оптовые каталоги, прайс-листы, отсрочка платежа | D7: Комус, Самсон-опт, ЧипДип
A8: SPEC | B8: Специализированные магазины элементов питания | C8: Моно-категорийные игроки: только батарейки, аккумуляторы, ЗУ | D8: Мир Батареек, Склад батареек, Баттерика
A9: QCOM | B9: Q-commerce и e-grocery доставка | C9: Быстрая доставка продуктов и товаров первой необходимости, витрина привязана к дарксторy/магазину | D9: Купер, Впрок, Самокат
A11: Классификация разработана под эту задачу: разделение по роли батарейки в ассортименте (основная категория / сопутствующая / импульсная покупка) и по модели продаж (1P, 3P, опт).
A12: «Выбор региона»: «Есть версии» = у региона отдельный URL (поддомен, префикс пути или ID магазина). «Единая карточка» = один URL на РФ, регион меняет только цену/наличие/сроки.

Sheet Сводка
A1: Сводка по реестру
A3: Направление | B3: Код | C3: Площадок | D3: Из них с региональными версиями
A4: Маркетплейс | B4: MP | C4: =COUNTIF(Продавцы!$D$2:$D$53,B4) | D4: =COUNTIFS(Продавцы!$D$2:$D$53,B4,Продавцы!$I$2:$I$53,"Есть версии")
A5: Электроника и бытовая техника | B5: EL | C5: =COUNTIF(Продавцы!$D$2:$D$53,B5) | D5: =COUNTIFS(Продавцы!$D$2:$D$53,B5,Продавцы!$I$2:$I$53,"Есть версии")
A6: Продукты и FMCG-ритейл | B6: FMCG | C6: =COUNTIF(Продавцы!$D$2:$D$53,B6) | D6: =COUNTIFS(Продавцы!$D$2:$D$53,B6,Продавцы!$I$2:$I$53,"Есть версии")
A7: DIY, ремонт и товары для дома | B7: DIY | C7: =COUNTIF(Продавцы!$D$2:$D$53,B7) | D7: =COUNTIFS(Продавцы!$D$2:$D$53,B7,Продавцы!$I$2:$I$53,"Есть версии")
A8: Дрогери и фикс-прайс | B8: DROG | C8: =COUNTIF(Продавцы!$D$2:$D$53,B8) | D8: =COUNTIFS(Продавцы!$D$2:$D$53,B8,Продавцы!$I$2:$I$53,"Есть версии")
A9: Офис, канцелярия и B2B-опт | B9: B2B | C9: =COUNTIF(Продавцы!$D$2:$D$53,B9) | D9: =COUNTIFS(Продавцы!$D$2:$D$53,B9,Продавцы!$I$2:$I$53,"Есть версии")
A10: Специализированные магазины элементов питания | B10: SPEC | C10: =COUNTIF(Продавцы!$D$2:$D$53,B10) | D10: =COUNTIFS(Продавцы!$D$2:$D$53,B10,Продавцы!$I$2:$I$53,"Есть версии")
A11: Q-commerce и e-grocery доставка | B11: QCOM | C11: =COUNTIF(Продавцы!$D$2:$D$53,B11) | D11: =COUNTIFS(Продавцы!$D$2:$D$53,B11,Продавцы!$I$2:$I$53,"Есть версии")
A12: ИТОГО | C12: =SUM(C4:C11) | D12: =SUM(D4:D11)
A14: Архитектура региональности
A15: Ответ | B15: Площадок
A16: Единая карточка | B16: =COUNTIF(Продавцы!$I$2:$I$53,A16)
A17: Есть версии | B17: =COUNTIF(Продавцы!$I$2:$I$53,A17)
A18: Требует уточнения | B18: =COUNTIF(Продавцы!$I$2:$I$53,A18)
A20: Источник данных: открытые каталоги площадок, сентябрь 2026. Поле «Статус проверки» на листе «Продавцы» показывает, что подтверждено напрямую, а что требует ручной перепроверки.
