Workbook

Sheet Сайты
A1: № | B1: Продавец / торговая сеть | C1: Домен | D1: Код | E1: Направление деятельности | F1: Подкатегория | G1: Тип игрока | H1: Бренды элементов питания | I1: СТМ | J1: Выбор региона | K1: Как устроена региональность | L1: Пример региональных URL | M1: Ссылка на страницу «Батарейки» | N1: Статус проверки | O1: Юрлиц в базе
A2: 1 | B2: AliExpress Россия | C2: aliexpress.ru | D2: MP | E2: Маркетплейсы и классифайды | F2: Универсальный маркетплейс | G2: Маркетплейс 3P (локальные + трансграничные) | H2: Азиатские марки + GP, Panasonic, SmartBuy | I2: Нет | J2: Единая карточка | K2: Единый URL товара, регион влияет на доступность локального склада | L2: — | M2: https://aliexpress.ru/ | N2: Требует уточнения (домен закрыт для краулера) | O2: 1
A3: 2 | B3: Ozon | C3: ozon.ru | D3: MP | E3: Маркетплейсы и классифайды | F3: Универсальный маркетплейс | G3: Маркетплейс 1P+3P | H3: Весь спектр: GP, Duracell, Energizer, Varta, Panasonic, Camelion, Kodak, Robiton, SmartBuy, ЭРА | I3: Нет | J3: Единая карточка | K3: Один URL карточки на всю РФ; регион меняет цену, срок и наличие, но не адрес страницы | L3: — | M3: https://www.ozon.ru/category/batareyki-15882/ | N3: Проверено | O3: 3
A4: 3 | B4: Wildberries | C4: wildberries.ru | D4: MP | E4: Маркетплейсы и классифайды | F4: Универсальный маркетплейс | G4: Маркетплейс 3P (юрлицо РВБ) | H4: Весь спектр: Duracell, Energizer, GP, Varta, Camelion, SmartBuy, Perfeo, ЭРА | I4: Нет | J4: Единая карточка | K4: Единый артикул на РФ; регион влияет на срок доставки до ПВЗ, URL неизменен | L4: — | M4: https://www.wildberries.ru/catalog/elektronika/tags/elementy-pitanija | N4: Проверено | O4: 3
A5: 4 | B5: Авито | C5: avito.ru | D5: MP | E5: Маркетплейсы и классифайды | F5: Классифайд + товарный маркетплейс | G5: Классифайд (юрлицо КЕХ еКоммерц) | H5: Разрозненный ассортимент от продавцов | I5: Нет | J5: Есть версии | K5: Объявление публикуется в конкретном городе; выдача и URL включают гео-сегмент | L5: avito.ru/moskva/... vs avito.ru/sankt-peterburg/... | M5: https://www.avito.ru/ | N5: Не проверено (сайт закрыт для краулера) | O5: 1
A6: 5 | B6: Магнит Маркет | C6: magnitmarket.ru | D6: MP | E6: Маркетплейсы и классифайды | F6: Универсальный маркетплейс | G6: Маркетплейс 3P (быв. KazanExpress, группа «Магнит») | H6: GP, Duracell, Energizer + СТМ «Магнит» | I6: Есть (СТМ «Магнит») | J6: Единая карточка | K6: Маркетплейс-логика: единый URL карточки, регион влияет на сроки | L6: — | M6: https://magnitmarket.ru/ | N6: Требует проверки глубокой ссылки | O6: 1
A7: 6 | B7: Мегамаркет | C7: megamarket.ru | D7: MP | E7: Маркетплейсы и классифайды | F7: Универсальный маркетплейс | G7: Маркетплейс 3P (экосистема Сбер) | H7: GP, Duracell, Energizer, Varta, АШАН Красная птица, Magnit | I7: Нет | J7: Единая карточка | K7: Единый URL категории и карточки, регион переключается селектором | L7: — | M7: https://megamarket.ru/catalog/batarejki/ | N7: Проверено | O7: 3
A8: 7 | B8: Яндекс Маркет | C8: market.yandex.ru | D8: MP | E8: Маркетплейсы и классифайды | F8: Универсальный маркетплейс | G8: Маркетплейс 3P + витрина сравнения | H8: Duracell, Energizer, GP, Kodak, Commo, Sonnen, Perfeo | I8: Commo (СТМ Яндекса) | J8: Единая карточка | K8: Карточка модели общая на РФ, региональность — в блоке офферов и сроках доставки | L8: — | M8: https://market.yandex.ru/catalog--batareiki-i-akkumuliatory-dlia-audio-i-videotekhniki/26914470/list | N8: Проверено | O8: 2
A9: 8 | B9: METRO Cash & Carry | C9: online.metro-cc.ru | D9: FMCG | E9: Продуктовый ритейл | F9: Мелкооптовый гипермаркет | G9: B2B+B2C формат | H9: Duracell, Energizer, GP, Varta, Panasonic + СТМ | I9: Есть (Aro, Rioba) | J9: Единая карточка | K9: Единый URL, торговый центр и город — селектором | L9: — | M9: https://online.metro-cc.ru/category/tovary-dlya-doma-dachi-sada/elektronika-i-tekhnika/batareyki-zaryadnye-ustroystva-fonariki | N9: Проверено | O9: 1
A10: 9 | B10: АТАК | C10: auchan.ru | D10: FMCG | E10: Продуктовый ритейл | F10: Супермаркеты | G10: Формат супермаркетов группы АШАН (ООО «АТАК») | H10: GP, Duracell, Energizer, АШАН Красная птица | I10: Есть («АШАН Красная птица») | J10: Единая карточка | K10: Онлайн-витрина сведена в auchan.ru; отдельные юрлица «АТАК» и «АТАК ПРИКАССА» в базе | L10: — | M10: https://www.auchan.ru/catalog/stroitelstvo-i-remont/elementy-pitaniya-i-fonari/batareyki/ | N10: Опознано по юрлицу (сеть работает, слухи об уходе АШАН официально опровергнуты) | O10: 2
A11: 10 | B11: АШАН | C11: auchan.ru | D11: FMCG | E11: Продуктовый ритейл | F11: Гипермаркеты + онлайн | G11: Федеральная сеть | H11: GP, Duracell, Energizer, Varta, АШАН Красная птица | I11: Есть («АШАН Красная птица») | J11: Единая карточка | K11: Единый URL категории; доставка в МСК, СПб, Ростов, Самару, Н.Новгород, Новосибирск, Краснодар, Татарстан | L11: — | M11: https://www.auchan.ru/catalog/stroitelstvo-i-remont/elementy-pitaniya-i-fonari/batareyki/ | N11: Проверено | O11: 2
A12: 11 | B12: Азбука Вкуса | C12: av.ru | D12: FMCG | E12: Продуктовый ритейл | F12: Премиальные супермаркеты | G12: Москва и СПб (ООО «Городской супермаркет») | H12: Duracell, GP, Energizer, Varta | I12: Есть | J12: Единая карточка | K12: Единый URL категории; доставка Москва и Санкт-Петербург | L12: — | M12: https://av.ru/catalog/dom-avto-dacha/batareyki-lampochki/ | N12: Проверено | O12: 1
A13: 12 | B13: Бегемаг | C13: begemag.ru | D13: FMCG | E13: Продуктовый ритейл | F13: Универсамы | G13: Кемеровская область | H13: GP, Duracell, Camelion | I13: Есть | J13: Требует уточнения | K13: Региональная сеть, онлайн-витрина не подтверждена | L13: — | M13: https://begemag.ru/ | N13: Требует проверки глубокой ссылки | O13: 1
... A104: 103 | B104: Яндекс Лавка | C104: lavka.yandex.ru | D104: QCOM | E104: Q-commerce, АЗС и travel retail | F104: Экспресс-доставка из даркстора | G104: ООО «Яндекс.Лавка» | H104: GP, Duracell + СТМ | I104: Есть (СТМ Яндекса) | J104: Есть версии | K104: Витрина привязана к дарксторy обслуживающего района | L104: — | M104: https://lavka.yandex.ru/ | N104: Требует проверки глубокой ссылки | O104: 1

Sheet Юрлица
A1: № | B1: Юрлицо из клиентской базы | C1: Тип записи | D1: Площадка / бренд | E1: Домен | F1: Направление | G1: Предполагаемый профиль | H1: Ссылка на страницу «Батарейки»
A2: 1 | B2: ТАНДЕР АО (5950) | C2: опознан | D2: Магнит | E2: magnit.ru | F2: Продуктовый ритейл | G2: Сети у дома и гипермаркеты | H2: https://www.magnit.ru/catalog/53067-batareyki
A3: 2 | B3: ООО «Интернет Решения» КОМИССИЯ | C3: опознан | D3: Ozon | E3: ozon.ru | F3: Маркетплейсы и классифайды | G3: Универсальный маркетплейс | H3: https://www.ozon.ru/category/batareyki-15882/
A4: 3 | B4: ДНС Ритейл ООО | C4: опознан | D4: DNS | E4: dns-shop.ru | F4: Электроника, техника и телеком | G4: Ритейл техники | H4: https://www.dns-shop.ru/catalog/17a88ded16404e77/batarejki/
A5: 4 | B5: КОМУС ООО | C5: опознан | D5: Комус | E5: komus.ru | F5: Опт, снабжение и дистрибуция | G5: Снабжение офиса и дома | H5: https://www.komus.ru/katalog/katalog-instrumentov/elektrika-i-svet/batarejki-akkumulyatory-zaryadnye-ustrojstva/batarejki/c/987489/
A6: 5 | B6: Бэст Прайс ООО | C6: опознан | D6: Fix Price | E6: fix-price.com | F6: Жёсткие дискаунтеры и офпрайс | G6: Магазины фиксированных цен | H6: https://fix-price.com/catalog/dlya-doma/p-5014027-batareyki-alkalinovye-aa-4-sht
A7: 6 | B7: ЛЕ МОНЛИД ООО | C7: опознан | D7: Леонардо | E7: leonardohobby.ru | F7: Нишевые категорийные сети | G7: Хобби и творчество | H7: https://leonardohobby.ru/ishop/tree_3811888309/
A8: 7 | B8: ООО «Оазис» | C8: не опознан | D8: требует поиска по ИНН | E8: — | F8: — | G8: профиль не определён | H8: —
A9: 8 | B9: ООО "РВБ", КОМИССИЯ 3P | C9: опознан | D9: Wildberries | E9: wildberries.ru | F9: Маркетплейсы и классифайды | G9: Универсальный маркетплейс | H9: https://www.wildberries.ru/catalog/elektronika/tags/elementy-pitanija
A10: 9 | B10: ЛЕНТА ООО | C10: опознан | D10: Лента | E10: lenta.com | F10: Продуктовый ритейл | G10: Гипер- и супермаркеты | H10: https://lenta.com/catalog/vse-dlya-doma/lampochki-elementy-pitaniya/elementy-pitaniya/
A11: 10 | B11: ООО «Агроторг» | C11: опознан | D11: Пятёрочка | E11: 5ka.ru | F11: Продуктовый ритейл | G11: Дискаунтер у дома | H11: https://5ka.ru/catalog/batareyki--251C12959/
A12: 11 | B12: АО "Торговый дом "ПЕРЕКРЕСТОК" | C12: опознан | D12: Перекрёсток | E12: perekrestok.ru | F12: Продуктовый ритейл | G12: Супермаркеты | H12: https://www.perekrestok.ru/cat/search?search=%D0%B1%D0%B0%D1%82%D0%B0%D1%80%D0%B5%D0%B9%D0%BA%D0%B8
A13: 12 | B13: ООО «Яндекс Маркет» КОМИССИЯ | C13: опознан | D13: Яндекс Маркет | E13: market.yandex.ru | F13: Маркетплейсы и классифайды | G13: Универсальный маркетплейс | H13: https://market.yandex.ru/catalog--batareiki-i-akkumuliatory-dlia-audio-i-videotekhniki/26914470/list
... A646: 645 | B646: ООО "Эй-Пи Трейд" | C646: не опознан | D646: требует поиска по ИНН | E646: — | F646: — | G646: Опт и дистрибуция | H646: —

Sheet Классификатор
A1: Код | B1: Направление деятельности | C1: Что относим | D1: Примеры
A2: MP | B2: Маркетплейсы и классифайды | C2: Площадки с внешними продавцами (3P) и/или собственной розницей (1P); категорию ведут селлеры | D2: Ozon, Wildberries, Яндекс Маркет, Авито
A3: FMCG | B3: Продуктовый ритейл | C3: Сети у дома, супермаркеты, гипермаркеты; батарейка — прикассовая и нон-фуд позиция | D3: Магнит, Пятёрочка, Лента, METRO
A4: HARD | B4: Жёсткие дискаунтеры и офпрайс | C4: Ультранизкий чек, узкая матрица, высокая доля СТМ и стоков | D4: Светофор, Маяк, Fix Price, Оффпрайс
A5: EL | B5: Электроника, техника и телеком | C5: Ритейл техники и салоны связи; батарейка — аксессуар к устройству | D5: DNS, М.Видео, Ситилинк, МТС
A6: DIY | B6: DIY, дом и ремонт | C6: Стройматериалы, электрика, инструмент, товары для дома | D6: Лемана ПРО, ВсеИнструменты, Петрович
A7: DROG | B7: Дрогери, косметика и парфюмерия | C7: Нон-фуд FMCG и бьюти; импульсная покупка у кассы | D7: Магнит Косметик, Улыбка радуги, Л'Этуаль
A8: B2B | B8: Опт, снабжение и дистрибуция | C8: Продажа юрлицам: канцелярия, электротехника, компоненты, мультикатегорийный опт | D8: Комус, ЭТМ, ЧипДип, Мерлион
A9: SPEC | B9: Специализированные по элементам питания | C9: Моно-категорийные игроки: только батарейки, аккумуляторы и ЗУ | D9: Мир Батареек, Баттерика, Киликс
A10: NICHE | B10: Нишевые категорийные сети | C10: Фото, музыка, хобби, спорт, зоо, медтехника, охрана, авто — батарейка как расходник к товару | D10: Леонардо, Исток-Аудио, Мир охоты
A11: QCOM | B11: Q-commerce, АЗС и travel retail | C11: Быстрая доставка и импульсные каналы вне классического магазина | D11: Самокат, Яндекс Лавка, АЗС, Почта России
A13: Классификация разработана под эту задачу: разделение по роли батарейки в ассортименте (основная категория / сопутствующая / импульсная покупка) и по модели продаж (1P, 3P, опт).
A14: «Выбор региона»: «Есть версии» = у региона отдельный URL (поддомен, префикс пути или ID магазина). «Единая карточка» = один URL на РФ, регион меняет только цену, наличие и сроки.
A15: Одна площадка может обслуживаться десятками юрлиц: у «Светофора» это ~30 региональных ООО «Торгсервис», где число в названии — код региона. Поэтому число юрлиц в базе не равно числу сайтов.

Sheet Сводка
A1: Сводка по реестру
A3: Направление | B3: Код | C3: Площадок | D3: С региональными версиями | E3: Юрлиц в базе
A4: Маркетплейсы и классифайды | B4: MP | C4: =COUNTIF(Сайты!$D$2:$D$104,B4) | D4: =COUNTIFS(Сайты!$D$2:$D$104,B4,Сайты!$J$2:$J$104,"Есть версии") | E4: =SUMIF(Сайты!$D$2:$D$104,B4,Сайты!$O$2:$O$104)
A5: Продуктовый ритейл | B5: FMCG | C5: =COUNTIF(Сайты!$D$2:$D$104,B5) | D5: =COUNTIFS(Сайты!$D$2:$D$104,B5,Сайты!$J$2:$J$104,"Есть версии") | E5: =SUMIF(Сайты!$D$2:$D$104,B5,Сайты!$O$2:$O$104)
A6: Жёсткие дискаунтеры и офпрайс | B6: HARD | C6: =COUNTIF(Сайты!$D$2:$D$104,B6) | D6: =COUNTIFS(Сайты!$D$2:$D$104,B6,Сайты!$J$2:$J$104,"Есть версии") | E6: =SUMIF(Сайты!$D$2:$D$104,B6,Сайты!$O$2:$O$104)
A7: Электроника, техника и телеком | B7: EL | C7: =COUNTIF(Сайты!$D$2:$D$104,B7) | D7: =COUNTIFS(Сайты!$D$2:$D$104,B7,Сайты!$J$2:$J$104,"Есть версии") | E7: =SUMIF(Сайты!$D$2:$D$104,B7,Сайты!$O$2:$O$104)
A8: DIY, дом и ремонт | B8: DIY | C8: =COUNTIF(Сайты!$D$2:$D$104,B8) | D8: =COUNTIFS(Сайты!$D$2:$D$104,B8,Сайты!$J$2:$J$104,"Есть версии") | E8: =SUMIF(Сайты!$D$2:$D$104,B8,Сайты!$O$2:$O$104)
A9: Дрогери, косметика и парфюмерия | B9: DROG | C9: =COUNTIF(Сайты!$D$2:$D$104,B9) | D9: =COUNTIFS(Сайты!$D$2:$D$104,B9,Сайты!$J$2:$J$104,"Есть версии") | E9: =SUMIF(Сайты!$D$2:$D$104,B9,Сайты!$O$2:$O$104)
A10: Опт, снабжение и дистрибуция | B10: B2B | C10: =COUNTIF(Сайты!$D$2:$D$104,B10) | D10: =COUNTIFS(Сайты!$D$2:$D$104,B10,Сайты!$J$2:$J$104,"Есть версии") | E10: =SUMIF(Сайты!$D$2:$D$104,B10,Сайты!$O$2:$O$104)
A11: Специализированные по элементам питания | B11: SPEC | C11: =COUNTIF(Сайты!$D$2:$D$104,B11) | D11: =COUNTIFS(Сайты!$D$2:$D$104,B11,Сайты!$J$2:$J$104,"Есть версии") | E11: =SUMIF(Сайты!$D$2:$D$104,B11,Сайты!$O$2:$O$104)
A12: Нишевые категорийные сети | B12: NICHE | C12: =COUNTIF(Сайты!$D$2:$D$104,B12) | D12: =COUNTIFS(Сайты!$D$2:$D$104,B12,Сайты!$J$2:$J$104,"Есть версии") | E12: =SUMIF(Сайты!$D$2:$D$104,B12,Сайты!$O$2:$O$104)
A13: Q-commerce, АЗС и travel retail | B13: QCOM | C13: =COUNTIF(Сайты!$D$2:$D$104,B13) | D13: =COUNTIFS(Сайты!$D$2:$D$104,B13,Сайты!$J$2:$J$104,"Есть версии") | E13: =SUMIF(Сайты!$D$2:$D$104,B13,Сайты!$O$2:$O$104)
A14: ИТОГО | C14: =SUM(C4:C13) | D14: =SUM(D4:D13) | E14: =SUM(E4:E13)
A16: Архитектура региональности
A17: Ответ | B17: Площадок
A18: Единая карточка | B18: =COUNTIF(Сайты!$J$2:$J$104,A18)
A19: Есть версии | B19: =COUNTIF(Сайты!$J$2:$J$104,A19)
A20: Требует уточнения | B20: =COUNTIF(Сайты!$J$2:$J$104,A20)
A22: Разбор клиентской базы юрлиц
A23: Тип записи | B23: Записей
A24: опознан | B24: =COUNTIF(Юрлица!$C$2:$C$646,A24)
A25: не опознан | B25: =COUNTIF(Юрлица!$C$2:$C$646,A25)
A26: сотрудник/ФИО | B26: =COUNTIF(Юрлица!$C$2:$C$646,A26)
A27: сотрудник | B27: =COUNTIF(Юрлица!$C$2:$C$646,A27)
A28: внутренний счёт | B28: =COUNTIF(Юрлица!$C$2:$C$646,A28)
A29: логистика (не розница) | B29: =COUNTIF(Юрлица!$C$2:$C$646,A29)
A30: не розница | B30: =COUNTIF(Юрлица!$C$2:$C$646,A30)
A31: ВСЕГО ЗАПИСЕЙ | B31: =SUM(B24:B30)
A33: Источник: открытые каталоги площадок + клиентская база юрлиц, сентябрь 2026. Колонка «Статус проверки» на листе «Сайты» показывает, что подтверждено напрямую.
